funcoesBasicas/__init__.py
funcoesBasicas/funcoes.py
funcoesbasicas-0.1.2.dist-info/licenses/LICENSE
funcoesbasicas-0.1.2.dist-info/METADATA
funcoesbasicas-0.1.2.dist-info/WHEEL
funcoesbasicas-0.1.2.dist-info/top_level.txt
funcoesbasicas-0.1.2.dist-info/RECORD
