Metadata-Version: 2.4
Name: funcoesBasicas
Version: 0.1.2
Summary: Biblioteca de funções básicas para projetos Python
Author: João Gabriel
Requires-Python: >=3.6
License-File: LICENSE
Dynamic: author
Dynamic: license-file
Dynamic: requires-python
Dynamic: summary
